generoo/__init__.py
generoo/__main__.py
generoo/generoo.py
generoo/utils.py
generoo/archetypes/java/spring-boot/2.0/.gitignore
generoo/archetypes/java/spring-boot/2.0/pom.xml
generoo/archetypes/java/spring-boot/2.0/project-template-config.json
generoo/archetypes/java/spring-boot/2.0/docker/Dockerfile
generoo/archetypes/java/spring-boot/2.0/docker/docker-build.sh
generoo/archetypes/java/spring-boot/2.0/docker/docker-run.sh
generoo/archetypes/java/spring-boot/2.0/{{#hibernate}}{{artifact_id}}-entity/pom.xml
generoo/archetypes/java/spring-boot/2.0/{{#hibernate}}{{artifact_id}}-entity/src/META-INF/persistence.xml
generoo/archetypes/java/spring-boot/2.0/{{#hibernate}}{{artifact_id}}-entity/src/main/java/{{group_id_slashes}}/{{artifact_id_periods}}/entity/{{artifact_id_capitalized}}Entity.java
generoo/archetypes/java/spring-boot/2.0/{{artifact_id}}-api/pom.xml
generoo/archetypes/java/spring-boot/2.0/{{artifact_id}}-api/src/main/java/{{group_id_slashes}}/{{artifact_id_slashes}}/{{artifact_id_capitalized}}Application.java
generoo/archetypes/java/spring-boot/2.0/{{artifact_id}}-api/src/main/java/{{group_id_slashes}}/{{artifact_id_slashes}}/api/{{artifact_id_capitalized}}Controller.java
generoo/archetypes/java/spring-boot/2.0/{{artifact_id}}-api/src/main/java/{{group_id_slashes}}/{{artifact_id_slashes}}/config/{{#hibernate}}DataConfig.java
generoo/archetypes/java/spring-boot/2.0/{{artifact_id}}-api/src/main/java/{{group_id_slashes}}/{{artifact_id_slashes}}/service/{{artifact_id_capitalized}}Service.java
generoo/archetypes/java/spring-boot/2.0/{{artifact_id}}-api/src/main/java/{{group_id_slashes}}/{{artifact_id_slashes}}/{{#hibernate}}repository/{{artifact_id_capitalized}}Repository.java
generoo/archetypes/java/spring-boot/2.0/{{artifact_id}}-api/src/main/resources/application.yaml
generoo/archetypes/java/spring-boot/2.0/{{artifact_id}}-api/src/test/java/{{group_id_slashes}}/{{artifact_id_slashes}}/service/{{artifact_id_capitalized}}ServiceImpTest.java
generoo-2019.7.24.6.dist-info/LICENSE
generoo-2019.7.24.6.dist-info/METADATA
generoo-2019.7.24.6.dist-info/WHEEL
generoo-2019.7.24.6.dist-info/top_level.txt
generoo-2019.7.24.6.dist-info/RECORD
