Metadata-Version: 2.1
Name: generoo
Version: 2019.7.24.6
Summary: Generate code without writing any.
Home-page: https://github.com/army-of-one/generoo
Author: Thomas Sickert
Author-email: thomas.sickert@gmail.com
License: UNKNOWN
Platform: UNKNOWN
Classifier: Programming Language :: Python :: 3
Classifier: License :: OSI Approved :: MIT License
Classifier: Operating System :: OS Independent
Requires-Python: >=3.6
Requires-Dist: altgraph (==0.16.1)
Requires-Dist: future (==0.17.1)
Requires-Dist: macholib (==1.11)
Requires-Dist: pefile (==2019.4.18)
Requires-Dist: pick (==0.6.4)
Requires-Dist: PyInstaller (==3.4)
Requires-Dist: pystache (==0.5.4)
Requires-Dist: PyYAML (==5.1)
Requires-Dist: regex (==2019.06.05)
